Workbook

Sheet Budget Tracker
A1: DEPARTMENTAL BUDGET VARIANCE ANALYSIS
A2: Prepared by: Praise Favour Ngong | Period: January – June 2025
A3: Department | B3: Category | C3: Annual Budget (FCFA) | D3: Q1 Actual (FCFA) | E3: Q2 Actual (FCFA) | F3: Total Actual (FCFA) | G3: Variance (FCFA) | H3: Status
A4: Finance | B4: Salaries & Benefits | C4: 48000000 | D4: 11500000 | E4: 12200000 | F4: =D4+E4 -> 23700000 | G4: =C4-F4 -> 24300000 | H4: =IF(F4>C4,"Over Budget",IF(F4/C4>0.8,"On Track","Under Utilized")) -> Under Utilized
A5: Finance | B5: Audit & Compliance | C5: 12000000 | D5: 2800000 | E5: 3100000 | F5: =D5+E5 -> 5900000 | G5: =C5-F5 -> 6100000 | H5: =IF(F5>C5,"Over Budget",IF(F5/C5>0.8,"On Track","Under Utilized")) -> Under Utilized
A6: Finance | B6: Software & Subscriptions | C6: 6000000 | D6: 1400000 | E6: 1600000 | F6: =D6+E6 -> 3000000 | G6: =C6-F6 -> 3000000 | H6: =IF(F6>C6,"Over Budget",IF(F6/C6>0.8,"On Track","Under Utilized")) -> Under Utilized
A7: Finance | B7: Office Supplies | C7: 2400000 | D7: 550000 | E7: 620000 | F7: =D7+E7 -> 1170000 | G7: =C7-F7 -> 1230000 | H7: =IF(F7>C7,"Over Budget",IF(F7/C7>0.8,"On Track","Under Utilized")) -> Under Utilized
A8: HR | B8: Salaries & Benefits | C8: 36000000 | D8: 8800000 | E8: 9200000 | F8: =D8+E8 -> 18000000 | G8: =C8-F8 -> 18000000 | H8: =IF(F8>C8,"Over Budget",IF(F8/C8>0.8,"On Track","Under Utilized")) -> Under Utilized
A9: HR | B9: Recruitment | C9: 4800000 | D9: 1500000 | E9: 800000 | F9: =D9+E9 -> 2300000 | G9: =C9-F9 -> 2500000 | H9: =IF(F9>C9,"Over Budget",IF(F9/C9>0.8,"On Track","Under Utilized")) -> Under Utilized
A10: HR | B10: Training & Development | C10: 6000000 | D10: 1200000 | E10: 1800000 | F10: =D10+E10 -> 3000000 | G10: =C10-F10 -> 3000000 | H10: =IF(F10>C10,"Over Budget",IF(F10/C10>0.8,"On Track","Under Utilized")) -> Under Utilized
A11: HR | B11: Staff Welfare | C11: 3600000 | D11: 750000 | E11: 900000 | F11: =D11+E11 -> 1650000 | G11: =C11-F11 -> 1950000 | H11: =IF(F11>C11,"Over Budget",IF(F11/C11>0.8,"On Track","Under Utilized")) -> Under Utilized
A12: Operations | B12: Rent & Utilities | C12: 18000000 | D12: 4400000 | E12: 4600000 | F12: =D12+E12 -> 9000000 | G12: =C12-F12 -> 9000000 | H12: =IF(F12>C12,"Over Budget",IF(F12/C12>0.8,"On Track","Under Utilized")) -> Under Utilized
A13: Operations | B13: Equipment Maintenance | C13: 7200000 | D13: 1900000 | E13: 2100000 | F13: =D13+E13 -> 4000000 | G13: =C13-F13 -> 3200000 | H13: =IF(F13>C13,"Over Budget",IF(F13/C13>0.8,"On Track","Under Utilized")) -> Under Utilized
A14: Operations | B14: Transportation | C14: 4800000 | D14: 1300000 | E14: 1100000 | F14: =D14+E14 -> 2400000 | G14: =C14-F14 -> 2400000 | H14: =IF(F14>C14,"Over Budget",IF(F14/C14>0.8,"On Track","Under Utilized")) -> Under Utilized
A15: Operations | B15: Security | C15: 3600000 | D15: 850000 | E15: 950000 | F15: =D15+E15 -> 1800000 | G15: =C15-F15 -> 1800000 | H15: =IF(F15>C15,"Over Budget",IF(F15/C15>0.8,"On Track","Under Utilized")) -> Under Utilized
... A21: IT | B21: IT Support | C21: 4800000 | D21: 1100000 | E21: 1300000 | F21: =D21+E21 -> 2400000 | G21: =C21-F21 -> 2400000 | H21: =IF(F21>C21,"Over Budget",IF(F21/C21>0.8,"On Track","Under Utilized")) -> Under Utilized
A22: GRAND TOTAL | C22: =SUM(C4:C21) -> 192000000 | D22: =SUM(D4:D21) -> 46850000 | E22: =SUM(E4:E21) -> 49170000 | F22: =SUM(F4:F21) -> 96020000 | G22: =SUM(G4:G21) -> 95980000 | H22: =IF(F22>C22,"Over Budget","Within Budget") -> Within Budget

Sheet Department Summary
A1: BUDGET SUMMARY BY DEPARTMENT H1 2025
A2: This summary is automatically pulled from the Budget Tracker sheet
A3: Department | B3: Total Budget (FCFA) | C3: Total Actual (FCFA) | D3: Variance (FCFA) | E3: Budget Used (%) | F3: Status
A4: Finance | B4: =SUMIF('Budget Tracker'!A:A,A4,'Budget Tracker'!C:C) -> 68400000 | C4: =SUMIF('Budget Tracker'!A:A,A4,'Budget Tracker'!F:F) -> 33770000 | D4: =B4-C4 -> 34630000 | E4: =C4/B4 -> 0.49371345 | F4: =IF(C4>B4,"Over Budget",IF(C4/B4>0.8,"On Track","Under Utilized")) -> Under Utilized
A5: HR | B5: =SUMIF('Budget Tracker'!A:A,A5,'Budget Tracker'!C:C) -> 50400000 | C5: =SUMIF('Budget Tracker'!A:A,A5,'Budget Tracker'!F:F) -> 24950000 | D5: =B5-C5 -> 25450000 | E5: =C5/B5 -> 0.49503968 | F5: =IF(C5>B5,"Over Budget",IF(C5/B5>0.8,"On Track","Under Utilized")) -> Under Utilized
A6: Operations | B6: =SUMIF('Budget Tracker'!A:A,A6,'Budget Tracker'!C:C) -> 33600000 | C6: =SUMIF('Budget Tracker'!A:A,A6,'Budget Tracker'!F:F) -> 17200000 | D6: =B6-C6 -> 16400000 | E6: =C6/B6 -> 0.51190476 | F6: =IF(C6>B6,"Over Budget",IF(C6/B6>0.8,"On Track","Under Utilized")) -> Under Utilized
A7: Marketing | B7: =SUMIF('Budget Tracker'!A:A,A7,'Budget Tracker'!C:C) -> 20400000 | C7: =SUMIF('Budget Tracker'!A:A,A7,'Budget Tracker'!F:F) -> 10800000 | D7: =B7-C7 -> 9600000 | E7: =C7/B7 -> 0.52941176 | F7: =IF(C7>B7,"Over Budget",IF(C7/B7>0.8,"On Track","Under Utilized")) -> Under Utilized
A8: IT | B8: =SUMIF('Budget Tracker'!A:A,A8,'Budget Tracker'!C:C) -> 19200000 | C8: =SUMIF('Budget Tracker'!A:A,A8,'Budget Tracker'!F:F) -> 9300000 | D8: =B8-C8 -> 9900000 | E8: =C8/B8 -> 0.484375 | F8: =IF(C8>B8,"Over Budget",IF(C8/B8>0.8,"On Track","Under Utilized")) -> Under Utilized
A9: TOTAL | B9: =SUM(B4:B8) -> 192000000 | C9: =SUM(C4:C8) -> 96020000 | D9: =SUM(D4:D8) -> 95980000 | E9: =C9/B9 -> 0.50010417 | F9: =IF(C9>B9,"Over Budget","Within Budget") -> Within Budget

Sheet Variance Analysis
A1: VARIANCE ANALYSIS REPORT H1 2025
A2: Department | B2: Budget (FCFA) | C2: Actual (FCFA) | D2: Variance (FCFA) | E2: Analysis Note
A3: Finance | B3: ='Department Summary'!B4 -> 68400000 | C3: ='Department Summary'!C4 -> 33770000 | D3: ='Department Summary'!D4 -> 34630000 | E3: Audit costs slightly higher due to additional compliance review requested by management.
A4: HR | B4: ='Department Summary'!B5 -> 50400000 | C4: ='Department Summary'!C5 -> 24950000 | D4: ='Department Summary'!D5 -> 25450000 | E4: Recruitment underspent as two planned hires were postponed to H2.
A5: Operations | B5: ='Department Summary'!B6 -> 33600000 | C5: ='Department Summary'!C6 -> 17200000 | D5: ='Department Summary'!D6 -> 16400000 | E5: Rent and utilities on track. Transportation underspent due to remote work policy.
A6: Marketing | B6: ='Department Summary'!B7 -> 20400000 | C6: ='Department Summary'!C7 -> 10800000 | D6: ='Department Summary'!D7 -> 9600000 | E6: Client events underspent. Advertising slightly over due to new campaign launch.
A7: IT | B7: ='Department Summary'!B8 -> 19200000 | C7: ='Department Summary'!C8 -> 9300000 | D7: ='Department Summary'!D8 -> 9900000 | E7: Hardware underspent as server upgrade was delayed to Q3.
